rts2/__init__.py
rts2/scriptcomm.py
RTS2-0.0.1.dist-info/LICENSE
RTS2-0.0.1.dist-info/METADATA
RTS2-0.0.1.dist-info/WHEEL
RTS2-0.0.1.dist-info/top_level.txt
RTS2-0.0.1.dist-info/RECORD
